extras/__init__.py
extras/divide.py
extras/multiply.py
vijaikfirstpackage-0.1.1.dist-info/METADATA
vijaikfirstpackage-0.1.1.dist-info/WHEEL
vijaikfirstpackage-0.1.1.dist-info/top_level.txt
vijaikfirstpackage-0.1.1.dist-info/RECORD
