Metadata-Version: 2.1
Name: vijaikfirstpackage
Version: 0.1.1
Summary: Setting up a python package
Author: Vijai Kannan
Author-email: vijaik.nd@gmail.com
License: UNKNOWN
Keywords: python,test package
Platform: UNKNOWN
Classifier: Development Status :: 3 - Alpha
Classifier: Intended Audience :: Education
Classifier: Programming Language :: Python :: 2
Classifier: Programming Language :: Python :: 3
Classifier: Operating System :: MacOS :: MacOS X
Classifier: Operating System :: Microsoft :: Windows
